{
	"category": [
		{
			"name": "home",
			"link": "hero",
			"offset": 0
		},
		{
			"name": "about",
			"link": "about",
			"offset": -120
		},
		{
			"name": "skills",
			"link": "skill",
			"offset": -120
		},
		{
			"name": "projects",
			"link": "projects",
			"offset": -120
		},
		{
			"name": "contact",
			"link": "contact",
			"offset": -120
		}
	],
	"social": [
		{
			"img": "https://raw.githubusercontent.com/kundankrgupta1/me.kundan/main/img/git.png",
			"link": "https://github.com/kundankrgupta1"
		},
		{
			"img": "https://raw.githubusercontent.com/kundankrgupta1/me.kundan/main/img/li.png",
			"link": "https://www.linkedin.com/in/kundankrgupta1/"
		},
		{
			"img": "https://raw.githubusercontent.com/kundankrgupta1/me.kundan/main/img/icons8-email-96.png",
			"link": "mailto:kundanprogrammerz@gmail.com"
		}
	]
}